ambient/__init__.py
ambient/air.py
ambient/base.py
ambient/boundary.py
ambient/io.py
ambient/location.py
ambient/material.py
ambient/simulation.py
ambient/sun.py
ambient/surface.py
ambient/time.py
ambient-0.0.1a1.dist-info/LICENSE
ambient-0.0.1a1.dist-info/METADATA
ambient-0.0.1a1.dist-info/WHEEL
ambient-0.0.1a1.dist-info/top_level.txt
ambient-0.0.1a1.dist-info/RECORD
