Metadata-Version: 2.1
Name: ambient
Version: 0.0.1a1
Summary: A package for building engineering physics
Home-page: UNKNOWN
License: Apache License, Version 2
Keywords: building engineering physics,psychrometrics
Platform: UNKNOWN
Classifier: Topic :: Scientific/Engineering :: Physics
Classifier: License :: OSI Approved :: Apache Software License
Requires-Dist: numpy
Requires-Dist: scipy
